mcp_ops_toolkit/__init__.py
mcp_ops_toolkit/main.py
mcp_ops_toolkit/pricing_calculator.py
mcp_ops_toolkit-0.1.3.dist-info/METADATA
mcp_ops_toolkit-0.1.3.dist-info/WHEEL
mcp_ops_toolkit-0.1.3.dist-info/entry_points.txt
mcp_ops_toolkit-0.1.3.dist-info/RECORD
